[{
    "id": 1,
    "question": "What is the primary goal of time management?",
    "options": {
      "a": "Increase stress levels",
      "b": "Increase productivity",
      "c": "Work longer hours",
      "d": "Take more breaks"
    },
    "answer": "b"
  },
  {
    "id": 2,
    "question": "Which of the following is an example of a time waster?",
    "options": {
      "a": "Focused work on important tasks",
      "b": "Excessive time on the internet",
      "c": "Prioritizing important projects",
      "d": "Setting SMART goals"
    },
    "answer": "b"
  },
  {
    "id": 3,
    "question": "Which principle states that 80% of results come from 20% of tasks?",
    "options": {
      "a": "The Parkinson’s Law",
      "b": "The Pareto Principle",
      "c": "The Time Matrix",
      "d": "The Law of Diminishing Returns"
    },
    "answer": "b"
  },
  {
    "id": 4,
    "question": "What should be prioritized when managing time effectively?",
    "options": {
      "a": "Urgent tasks",
      "b": "Important tasks",
      "c": "Non-essential tasks",
      "d": "Tasks that require the least effort"
    },
    "answer": "b"
  },
  {
    "id": 5,
    "question": "Which of the following is NOT a mistake in time management?",
    "options": {
      "a": "Setting personal goals",
      "b": "Procrastination",
      "c": "Multitasking",
      "d": "Not managing distractions"
    },
    "answer": "a"
  },
  {
    "id": 6,
    "question": "What is the main reason for making a to-do list?",
    "options": {
      "a": "To prioritize tasks",
      "b": "To keep track of social media updates",
      "c": "To list all distractions",
      "d": "To track time spent on each task"
    },
    "answer": "a"
  },
  {
    "id": 7,
    "question": "What is a key factor for avoiding burnout due to poor time management?",
    "options": {
      "a": "Working without breaks",
      "b": "Taking on too many tasks",
      "c": "Setting boundaries and learning to say no",
      "d": "Procrastinating tasks until the last minute"
    },
    "answer": "c"
  },
  {
    "id": 8,
    "question": "Which of the following is an essential skill for time management?",
    "options": {
      "a": "Multitasking",
      "b": "Self-awareness",
      "c": "Ignoring deadlines",
      "d": "Constantly working without rest"
    },
    "answer": "b"
  },
  {
    "id": 9,
    "question": "Why is it important to schedule relaxation time when managing time?",
    "options": {
      "a": "To avoid distractions",
      "b": "To prevent burnout and refresh the mind",
      "c": "To waste time",
      "d": "To take unnecessary breaks"
    },
    "answer": "b"
  },
  {
    "id": 10,
    "question": "Which mistake can lead to poor time management when dealing with tasks?",
    "options": {
      "a": "Breaking down large tasks into manageable steps",
      "b": "Not prioritizing tasks",
      "c": "Setting clear goals",
      "d": "Creating and reviewing schedules"
    },
    "answer": "b"
  }
]
